Overlap_BMS_1/__init__.py
Overlap_BMS_1-0.7.dist-info/METADATA
Overlap_BMS_1-0.7.dist-info/WHEEL
Overlap_BMS_1-0.7.dist-info/top_level.txt
Overlap_BMS_1-0.7.dist-info/RECORD
